{
  "avg_typing_gap": 0.24521643161773682,
  "avg_mouse_speed": 5.620789952863036,
  "active_hours": [
    9
  ],
  "typical_apps": [
    "M365Copilot.exe",
    "IntelCpHDCPSvc.exe",
    "WidgetService.exe",
    "crashpad_handler.exe",
    "ai.exe",
    "taskhostw.exe",
    "SgrmBroker.exe",
    "cowork-svc.exe",
    "IntelCpHeciSvc.exe",
    "sihost.exe",
    "UserOOBEBroker.exe",
    "dllhost.exe",
    "Notepad.exe",
    "LsaIso.exe",
    "System Idle Process",
    "winlogon.exe",
    "MsMpEng.exe",
    "GameInputRedistService.exe",
    "pet.exe",
    "StartMenuExperienceHost.exe",
    "TextInputHost.exe",
    "openvpnserv.exe",
    "csrss.exe",
    "RuntimeBroker.exe",
    "OneDrive.Sync.Service.exe",
    "Registry",
    "System",
    "gamingservicesnet.exe",
    "spoolsv.exe",
    "openvpnserv2.exe",
    "WavesSysSvc64.exe",
    "mongod.exe",
    "OfficeClickToRun.exe",
    "GoogleDriveFS.exe",
    "python.exe",
    "igfxCUIService.exe",
    "OneApp.IGCC.WinService.exe",
    "SDXHelper.exe",
    "Code.exe",
    "ibtsiva.exe",
    "explorer.exe",
    "SecurityHealthService.exe",
    "ms-teams.exe",
    "services.exe",
    "msedgewebview2.exe",
    "SearchIndexer.exe",
    "gamingservices.exe",
    "smss.exe",
    "Widgets.exe",
    "fontdrvhost.exe",
    "powershell.exe",
    "PresentationFontCache.exe",
    "chrome.exe",
    "SearchProtocolHost.exe",
    "conhost.exe",
    "RtkAudioService64.exe",
    "MemCompression",
    "MpDefenderCoreService.exe",
    "dwm.exe",
    "ApplicationFrameHost.exe",
    "RAVBg64.exe",
    "BraveCrashHandler.exe",
    "lsass.exe",
    "LMS.exe",
    "vmcompute.exe",
    "jhi_service.exe",
    "ShellExperienceHost.exe",
    "AggregatorHost.exe",
    "WINWORD.EXE",
    "igfxEM.exe",
    "BraveCrashHandler64.exe",
    "NisSrv.exe",
    "ctfmon.exe",
    "wininit.exe",
    "svchost.exe"
  ],
  "avg_cpu": 20.3,
  "recorded_at": "2026-06-28 09:57:01"
}